us_sewersheds/__init__.py
us_sewersheds/marimo_app_archive.py
us_sewersheds/merge_cwns_data.py
us_sewersheds/plotting_configs.py
us_sewersheds/sewersheds_app.py
us_sewersheds-0.1.2.dist-info/METADATA
us_sewersheds-0.1.2.dist-info/WHEEL
us_sewersheds-0.1.2.dist-info/top_level.txt
us_sewersheds-0.1.2.dist-info/RECORD
