Metadata-Version: 2.4
Name: us-sewersheds
Version: 0.1.2
Summary: Process and analyze US sewershed data from CWNS
Author-email: Daly Wettermark <139182397+dalyw@users.noreply.github.com>
License-Expression: MIT
Project-URL: Homepage, https://github.com/dalyw/us-sewersheds
Project-URL: Repository, https://github.com/dalyw/us-sewersheds
Keywords: sewersheds,wastewater,CWNS,data
Classifier: Development Status :: 3 - Alpha
Classifier: Intended Audience :: Science/Research
Classifier: Programming Language :: Python :: 3
Classifier: Programming Language :: Python :: 3.11
Classifier: Programming Language :: Python :: 3.12
Requires-Python: >=3.11
Requires-Dist: pandas>=2.2.3
Requires-Dist: networkx>=3.4.2
Requires-Dist: numpy>=2.2.2
Requires-Dist: streamlit>=1.42.0
Requires-Dist: plotly>=5.20.0
Requires-Dist: dash>=2.18.2
Requires-Dist: dash_cytoscape>=1.0.2
Requires-Dist: urllib3>=2.0.0
Provides-Extra: dev
Requires-Dist: pytest; extra == "dev"
Requires-Dist: flake8; extra == "dev"
Requires-Dist: black; extra == "dev"
Requires-Dist: bumpversion; extra == "dev"
